nonebot_plugin_joke/__init__.py
nonebot_plugin_joke/get_joke.py
nonebot_plugin_joke-0.1.0.dist-info/LICENSE
nonebot_plugin_joke-0.1.0.dist-info/METADATA
nonebot_plugin_joke-0.1.0.dist-info/WHEEL
nonebot_plugin_joke-0.1.0.dist-info/RECORD
