Metadata-Version: 2.3
Name: nonebot-plugin-joke
Version: 0.1.0
Summary: nonebot2插件：讲中英文笑话
License: MIT
Author: Elden
Author-email: h_elden@qq.com
Requires-Python: >=3.9
Classifier: License :: OSI Approved :: MIT License
Classifier: Programming Language :: Python :: 3
Classifier: Programming Language :: Python :: 3.9
Classifier: Programming Language :: Python :: 3.10
Classifier: Programming Language :: Python :: 3.11
Classifier: Programming Language :: Python :: 3.12
Classifier: Programming Language :: Python :: 3.13
Requires-Dist: httpx (>=0.28.1,<1.0.0)
Requires-Dist: nonebot-adapter-onebot (>=2.4.6,<3.0.0)
Requires-Dist: nonebot2 (>=2.3.0,<3.0.0)
